[
  {
    "pace_rank": 1,
    "Driver": "HAM",
    "Team": "Mercedes",
    "DriverNumber": "44",
    "clean_laps": 46,
    "average_lap_seconds": 106.368,
    "median_lap_seconds": 105.785,
    "best_lap_seconds": 104.166,
    "lap_time_std_seconds": 1.502,
    "gap_to_best_avg_seconds": 0.0
  },
  {
    "pace_rank": 2,
    "Driver": "VER",
    "Team": "Red Bull Racing",
    "DriverNumber": "33",
    "clean_laps": 46,
    "average_lap_seconds": 106.662,
    "median_lap_seconds": 105.868,
    "best_lap_seconds": 104.794,
    "lap_time_std_seconds": 1.63,
    "gap_to_best_avg_seconds": 0.294
  },
  {
    "pace_rank": 3,
    "Driver": "VET",
    "Team": "Ferrari",
    "DriverNumber": "5",
    "clean_laps": 46,
    "average_lap_seconds": 106.59,
    "median_lap_seconds": 106.03,
    "best_lap_seconds": 104.629,
    "lap_time_std_seconds": 1.4,
    "gap_to_best_avg_seconds": 0.222
  },
  {
    "pace_rank": 4,
    "Driver": "BOT",
    "Team": "Mercedes",
    "DriverNumber": "77",
    "clean_laps": 46,
    "average_lap_seconds": 106.392,
    "median_lap_seconds": 106.09,
    "best_lap_seconds": 104.024,
    "lap_time_std_seconds": 1.302,
    "gap_to_best_avg_seconds": 0.024
  },
  {
    "pace_rank": 5,
    "Driver": "LEC",
    "Team": "Ferrari",
    "DriverNumber": "16",
    "clean_laps": 44,
    "average_lap_seconds": 107.415,
    "median_lap_seconds": 107.32,
    "best_lap_seconds": 103.009,
    "lap_time_std_seconds": 1.824,
    "gap_to_best_avg_seconds": 1.047
  },
  {
    "pace_rank": 6,
    "Driver": "GAS",
    "Team": "Red Bull Racing",
    "DriverNumber": "10",
    "clean_laps": 35,
    "average_lap_seconds": 107.658,
    "median_lap_seconds": 107.389,
    "best_lap_seconds": 105.712,
    "lap_time_std_seconds": 1.604,
    "gap_to_best_avg_seconds": 1.29
  },
  {
    "pace_rank": 7,
    "Driver": "SAI",
    "Team": "McLaren",
    "DriverNumber": "55",
    "clean_laps": 46,
    "average_lap_seconds": 107.987,
    "median_lap_seconds": 107.432,
    "best_lap_seconds": 105.807,
    "lap_time_std_seconds": 1.664,
    "gap_to_best_avg_seconds": 1.619
  },
  {
    "pace_rank": 8,
    "Driver": "PER",
    "Team": "Racing Point",
    "DriverNumber": "11",
    "clean_laps": 46,
    "average_lap_seconds": 107.854,
    "median_lap_seconds": 107.61,
    "best_lap_seconds": 105.524,
    "lap_time_std_seconds": 1.745,
    "gap_to_best_avg_seconds": 1.486
  },
  {
    "pace_rank": 9,
    "Driver": "NOR",
    "Team": "McLaren",
    "DriverNumber": "4",
    "clean_laps": 44,
    "average_lap_seconds": 107.827,
    "median_lap_seconds": 107.638,
    "best_lap_seconds": 105.394,
    "lap_time_std_seconds": 1.277,
    "gap_to_best_avg_seconds": 1.459
  },
  {
    "pace_rank": 10,
    "Driver": "STR",
    "Team": "Racing Point",
    "DriverNumber": "18",
    "clean_laps": 46,
    "average_lap_seconds": 108.223,
    "median_lap_seconds": 107.929,
    "best_lap_seconds": 106.009,
    "lap_time_std_seconds": 1.779,
    "gap_to_best_avg_seconds": 1.855
  },
  {
    "pace_rank": 11,
    "Driver": "RIC",
    "Team": "Renault",
    "DriverNumber": "3",
    "clean_laps": 26,
    "average_lap_seconds": 108.921,
    "median_lap_seconds": 108.232,
    "best_lap_seconds": 106.767,
    "lap_time_std_seconds": 1.633,
    "gap_to_best_avg_seconds": 2.553
  },
  {
    "pace_rank": 12,
    "Driver": "ALB",
    "Team": "Toro Rosso",
    "DriverNumber": "23",
    "clean_laps": 45,
    "average_lap_seconds": 108.75,
    "median_lap_seconds": 108.27,
    "best_lap_seconds": 105.754,
    "lap_time_std_seconds": 2.068,
    "gap_to_best_avg_seconds": 2.382
  },
  {
    "pace_rank": 13,
    "Driver": "GIO",
    "Team": "Alfa Romeo Racing",
    "DriverNumber": "99",
    "clean_laps": 45,
    "average_lap_seconds": 108.728,
    "median_lap_seconds": 108.415,
    "best_lap_seconds": 105.969,
    "lap_time_std_seconds": 2.128,
    "gap_to_best_avg_seconds": 2.36
  },
  {
    "pace_rank": 14,
    "Driver": "RAI",
    "Team": "Alfa Romeo Racing",
    "DriverNumber": "7",
    "clean_laps": 44,
    "average_lap_seconds": 108.424,
    "median_lap_seconds": 108.488,
    "best_lap_seconds": 106.479,
    "lap_time_std_seconds": 1.193,
    "gap_to_best_avg_seconds": 2.056
  },
  {
    "pace_rank": 15,
    "Driver": "KVY",
    "Team": "Toro Rosso",
    "DriverNumber": "26",
    "clean_laps": 28,
    "average_lap_seconds": 109.279,
    "median_lap_seconds": 108.786,
    "best_lap_seconds": 107.681,
    "lap_time_std_seconds": 1.897,
    "gap_to_best_avg_seconds": 2.911
  },
  {
    "pace_rank": 16,
    "Driver": "MAG",
    "Team": "Haas F1 Team",
    "DriverNumber": "20",
    "clean_laps": 43,
    "average_lap_seconds": 108.952,
    "median_lap_seconds": 108.838,
    "best_lap_seconds": 106.682,
    "lap_time_std_seconds": 1.316,
    "gap_to_best_avg_seconds": 2.584
  },
  {
    "pace_rank": 17,
    "Driver": "HUL",
    "Team": "Renault",
    "DriverNumber": "27",
    "clean_laps": 43,
    "average_lap_seconds": 109.673,
    "median_lap_seconds": 108.963,
    "best_lap_seconds": 107.407,
    "lap_time_std_seconds": 2.203,
    "gap_to_best_avg_seconds": 3.305
  },
  {
    "pace_rank": 18,
    "Driver": "GRO",
    "Team": "Haas F1 Team",
    "DriverNumber": "8",
    "clean_laps": 33,
    "average_lap_seconds": 110.382,
    "median_lap_seconds": 110.253,
    "best_lap_seconds": 108.517,
    "lap_time_std_seconds": 1.527,
    "gap_to_best_avg_seconds": 4.014
  },
  {
    "pace_rank": 19,
    "Driver": "KUB",
    "Team": "Williams",
    "DriverNumber": "88",
    "clean_laps": 39,
    "average_lap_seconds": 110.723,
    "median_lap_seconds": 110.607,
    "best_lap_seconds": 107.709,
    "lap_time_std_seconds": 1.496,
    "gap_to_best_avg_seconds": 4.355
  },
  {
    "pace_rank": 20,
    "Driver": "RUS",
    "Team": "Williams",
    "DriverNumber": "63",
    "clean_laps": 42,
    "average_lap_seconds": 110.381,
    "median_lap_seconds": 110.796,
    "best_lap_seconds": 107.251,
    "lap_time_std_seconds": 1.754,
    "gap_to_best_avg_seconds": 4.013
  }
]