[
  {
    "year": 1965,
    "position": 1,
    "position_text": "1",
    "points": 54.0,
    "wins": 6,
    "constructor_id": "lotus-climax",
    "constructor": "Lotus-Climax",
    "constructor_nationality": "British",
    "constructor_url": "https://en.wikipedia.org/wiki/Team_Lotus"
  },
  {
    "year": 1965,
    "position": 2,
    "position_text": "2",
    "points": 45.0,
    "wins": 3,
    "constructor_id": "brm",
    "constructor": "BRM",
    "constructor_nationality": "British",
    "constructor_url": "https://en.wikipedia.org/wiki/British_Racing_Motors"
  },
  {
    "year": 1965,
    "position": 3,
    "position_text": "3",
    "points": 27.0,
    "wins": 0,
    "constructor_id": "brabham-climax",
    "constructor": "Brabham-Climax",
    "constructor_nationality": "British",
    "constructor_url": "https://en.wikipedia.org/wiki/Brabham"
  },
  {
    "year": 1965,
    "position": 4,
    "position_text": "4",
    "points": 26.0,
    "wins": 0,
    "constructor_id": "ferrari",
    "constructor": "Ferrari",
    "constructor_nationality": "Italian",
    "constructor_url": "https://en.wikipedia.org/wiki/Scuderia_Ferrari"
  },
  {
    "year": 1965,
    "position": 5,
    "position_text": "5",
    "points": 14.0,
    "wins": 0,
    "constructor_id": "cooper-climax",
    "constructor": "Cooper-Climax",
    "constructor_nationality": "British",
    "constructor_url": "https://en.wikipedia.org/wiki/Cooper_Car_Company"
  },
  {
    "year": 1965,
    "position": 6,
    "position_text": "6",
    "points": 11.0,
    "wins": 1,
    "constructor_id": "honda",
    "constructor": "Honda",
    "constructor_nationality": "Japanese",
    "constructor_url": "https://en.wikipedia.org/wiki/Honda_in_Formula_One"
  },
  {
    "year": 1965,
    "position": 7,
    "position_text": "7",
    "points": 5.0,
    "wins": 0,
    "constructor_id": "brabham-brm",
    "constructor": "Brabham-BRM",
    "constructor_nationality": "British",
    "constructor_url": "https://en.wikipedia.org/wiki/Brabham"
  },
  {
    "year": 1965,
    "position": 8,
    "position_text": "8",
    "points": 2.0,
    "wins": 0,
    "constructor_id": "lotus-brm",
    "constructor": "Lotus-BRM",
    "constructor_nationality": "British",
    "constructor_url": "https://en.wikipedia.org/wiki/Team_Lotus"
  },
  {
    "year": 1965,
    "position": null,
    "position_text": "-",
    "points": 0.0,
    "wins": 0,
    "constructor_id": "brabham-ford",
    "constructor": "Brabham-Ford",
    "constructor_nationality": "British",
    "constructor_url": "https://en.wikipedia.org/wiki/Brabham"
  },
  {
    "year": 1965,
    "position": null,
    "position_text": "-",
    "points": 0.0,
    "wins": 0,
    "constructor_id": "alfa",
    "constructor": "Alfa Romeo",
    "constructor_nationality": "Swiss",
    "constructor_url": "https://en.wikipedia.org/wiki/Alfa_Romeo_in_Formula_One"
  },
  {
    "year": 1965,
    "position": null,
    "position_text": "-",
    "points": 0.0,
    "wins": 0,
    "constructor_id": "lds-alfa_romeo",
    "constructor": "LDS-Alfa Romeo",
    "constructor_nationality": "South African",
    "constructor_url": "https://en.wikipedia.org/wiki/LDS_(automobile)"
  },
  {
    "year": 1965,
    "position": null,
    "position_text": "-",
    "points": 0.0,
    "wins": 0,
    "constructor_id": "re",
    "constructor": "RE",
    "constructor_nationality": "Rhodesian",
    "constructor_url": "https://en.wikipedia.org/wiki/Realpha"
  },
  {
    "year": 1965,
    "position": null,
    "position_text": "-",
    "points": 0.0,
    "wins": 0,
    "constructor_id": "cooper-maserati",
    "constructor": "Cooper-Maserati",
    "constructor_nationality": "British",
    "constructor_url": "https://en.wikipedia.org/wiki/Cooper_Car_Company"
  }
]