{
  "year": 2024,
  "round": 5,
  "event_input": "Chinese Grand Prix",
  "event_name": "Chinese Grand Prix",
  "official_event_name": "FORMULA 1 LENOVO CHINESE GRAND PRIX 2024",
  "country": "China",
  "location": "Shanghai",
  "event_slug": "chinese-grand-prix",
  "session_input": "Race",
  "session_slug": "race",
  "generated_output_dir": "/Users/light/jarvis/00 Light/Projects/f1-stats-site/data-pipeline/output/events/2024/chinese-grand-prix/race",
  "source": "FastF1",
  "rows_laps": 1007,
  "drivers": [
    "ALB",
    "ALO",
    "BOT",
    "GAS",
    "HAM",
    "HUL",
    "LEC",
    "MAG",
    "NOR",
    "OCO",
    "PER",
    "PIA",
    "RIC",
    "RUS",
    "SAI",
    "SAR",
    "STR",
    "TSU",
    "VER",
    "ZHO"
  ],
  "rows_clean_laps": 878,
  "rows_pace": 20,
  "rows_stints": 60,
  "rows_pit_stops": 39,
  "rows_tyre_usage": 3
}