[
  {
    "year": 2022,
    "position": 1,
    "position_text": "1",
    "points": 454.0,
    "wins": 15,
    "driver_id": "max_verstappen",
    "driver_code": "VER",
    "driver_number": "3",
    "driver_name": "Max Verstappen",
    "driver_nationality": "Dutch",
    "constructors": [
      "Red Bull"
    ],
    "constructor_ids": [
      "red_bull"
    ]
  },
  {
    "year": 2022,
    "position": 2,
    "position_text": "2",
    "points": 308.0,
    "wins": 3,
    "driver_id": "leclerc",
    "driver_code": "LEC",
    "driver_number": "16",
    "driver_name": "Charles Leclerc",
    "driver_nationality": "Monegasque",
    "constructors": [
      "Ferrari"
    ],
    "constructor_ids": [
      "ferrari"
    ]
  },
  {
    "year": 2022,
    "position": 3,
    "position_text": "3",
    "points": 305.0,
    "wins": 2,
    "driver_id": "perez",
    "driver_code": "PER",
    "driver_number": "11",
    "driver_name": "Sergio P\u00e9rez",
    "driver_nationality": "Mexican",
    "constructors": [
      "Red Bull"
    ],
    "constructor_ids": [
      "red_bull"
    ]
  },
  {
    "year": 2022,
    "position": 4,
    "position_text": "4",
    "points": 275.0,
    "wins": 1,
    "driver_id": "russell",
    "driver_code": "RUS",
    "driver_number": "63",
    "driver_name": "George Russell",
    "driver_nationality": "British",
    "constructors": [
      "Mercedes"
    ],
    "constructor_ids": [
      "mercedes"
    ]
  },
  {
    "year": 2022,
    "position": 5,
    "position_text": "5",
    "points": 246.0,
    "wins": 1,
    "driver_id": "sainz",
    "driver_code": "SAI",
    "driver_number": "55",
    "driver_name": "Carlos Sainz",
    "driver_nationality": "Spanish",
    "constructors": [
      "Ferrari"
    ],
    "constructor_ids": [
      "ferrari"
    ]
  },
  {
    "year": 2022,
    "position": 6,
    "position_text": "6",
    "points": 240.0,
    "wins": 0,
    "driver_id": "hamilton",
    "driver_code": "HAM",
    "driver_number": "44",
    "driver_name": "Lewis Hamilton",
    "driver_nationality": "British",
    "constructors": [
      "Mercedes"
    ],
    "constructor_ids": [
      "mercedes"
    ]
  },
  {
    "year": 2022,
    "position": 7,
    "position_text": "7",
    "points": 122.0,
    "wins": 0,
    "driver_id": "norris",
    "driver_code": "NOR",
    "driver_number": "1",
    "driver_name": "Lando Norris",
    "driver_nationality": "British",
    "constructors": [
      "McLaren"
    ],
    "constructor_ids": [
      "mclaren"
    ]
  },
  {
    "year": 2022,
    "position": 8,
    "position_text": "8",
    "points": 92.0,
    "wins": 0,
    "driver_id": "ocon",
    "driver_code": "OCO",
    "driver_number": "31",
    "driver_name": "Esteban Ocon",
    "driver_nationality": "French",
    "constructors": [
      "Alpine F1 Team"
    ],
    "constructor_ids": [
      "alpine"
    ]
  },
  {
    "year": 2022,
    "position": 9,
    "position_text": "9",
    "points": 81.0,
    "wins": 0,
    "driver_id": "alonso",
    "driver_code": "ALO",
    "driver_number": "14",
    "driver_name": "Fernando Alonso",
    "driver_nationality": "Spanish",
    "constructors": [
      "Alpine F1 Team"
    ],
    "constructor_ids": [
      "alpine"
    ]
  },
  {
    "year": 2022,
    "position": 10,
    "position_text": "10",
    "points": 49.0,
    "wins": 0,
    "driver_id": "bottas",
    "driver_code": "BOT",
    "driver_number": "77",
    "driver_name": "Valtteri Bottas",
    "driver_nationality": "Finnish",
    "constructors": [
      "Alfa Romeo"
    ],
    "constructor_ids": [
      "alfa"
    ]
  },
  {
    "year": 2022,
    "position": 11,
    "position_text": "11",
    "points": 37.0,
    "wins": 0,
    "driver_id": "ricciardo",
    "driver_code": "RIC",
    "driver_number": "3",
    "driver_name": "Daniel Ricciardo",
    "driver_nationality": "Australian",
    "constructors": [
      "McLaren"
    ],
    "constructor_ids": [
      "mclaren"
    ]
  },
  {
    "year": 2022,
    "position": 12,
    "position_text": "12",
    "points": 37.0,
    "wins": 0,
    "driver_id": "vettel",
    "driver_code": "VET",
    "driver_number": "5",
    "driver_name": "Sebastian Vettel",
    "driver_nationality": "German",
    "constructors": [
      "Aston Martin"
    ],
    "constructor_ids": [
      "aston_martin"
    ]
  },
  {
    "year": 2022,
    "position": 13,
    "position_text": "13",
    "points": 25.0,
    "wins": 0,
    "driver_id": "kevin_magnussen",
    "driver_code": "MAG",
    "driver_number": "20",
    "driver_name": "Kevin Magnussen",
    "driver_nationality": "Danish",
    "constructors": [
      "Haas F1 Team"
    ],
    "constructor_ids": [
      "haas"
    ]
  },
  {
    "year": 2022,
    "position": 14,
    "position_text": "14",
    "points": 23.0,
    "wins": 0,
    "driver_id": "gasly",
    "driver_code": "GAS",
    "driver_number": "10",
    "driver_name": "Pierre Gasly",
    "driver_nationality": "French",
    "constructors": [
      "AlphaTauri"
    ],
    "constructor_ids": [
      "alphatauri"
    ]
  },
  {
    "year": 2022,
    "position": 15,
    "position_text": "15",
    "points": 18.0,
    "wins": 0,
    "driver_id": "stroll",
    "driver_code": "STR",
    "driver_number": "18",
    "driver_name": "Lance Stroll",
    "driver_nationality": "Canadian",
    "constructors": [
      "Aston Martin"
    ],
    "constructor_ids": [
      "aston_martin"
    ]
  },
  {
    "year": 2022,
    "position": 16,
    "position_text": "16",
    "points": 12.0,
    "wins": 0,
    "driver_id": "mick_schumacher",
    "driver_code": "MSC",
    "driver_number": "47",
    "driver_name": "Mick Schumacher",
    "driver_nationality": "German",
    "constructors": [
      "Haas F1 Team"
    ],
    "constructor_ids": [
      "haas"
    ]
  },
  {
    "year": 2022,
    "position": 17,
    "position_text": "17",
    "points": 12.0,
    "wins": 0,
    "driver_id": "tsunoda",
    "driver_code": "TSU",
    "driver_number": "22",
    "driver_name": "Yuki Tsunoda",
    "driver_nationality": "Japanese",
    "constructors": [
      "AlphaTauri"
    ],
    "constructor_ids": [
      "alphatauri"
    ]
  },
  {
    "year": 2022,
    "position": 18,
    "position_text": "18",
    "points": 6.0,
    "wins": 0,
    "driver_id": "zhou",
    "driver_code": "ZHO",
    "driver_number": "24",
    "driver_name": "Guanyu Zhou",
    "driver_nationality": "Chinese",
    "constructors": [
      "Alfa Romeo"
    ],
    "constructor_ids": [
      "alfa"
    ]
  },
  {
    "year": 2022,
    "position": 19,
    "position_text": "19",
    "points": 4.0,
    "wins": 0,
    "driver_id": "albon",
    "driver_code": "ALB",
    "driver_number": "23",
    "driver_name": "Alexander Albon",
    "driver_nationality": "Thai",
    "constructors": [
      "Williams"
    ],
    "constructor_ids": [
      "williams"
    ]
  },
  {
    "year": 2022,
    "position": 20,
    "position_text": "20",
    "points": 2.0,
    "wins": 0,
    "driver_id": "latifi",
    "driver_code": "LAT",
    "driver_number": "6",
    "driver_name": "Nicholas Latifi",
    "driver_nationality": "Canadian",
    "constructors": [
      "Williams"
    ],
    "constructor_ids": [
      "williams"
    ]
  },
  {
    "year": 2022,
    "position": 21,
    "position_text": "21",
    "points": 2.0,
    "wins": 0,
    "driver_id": "de_vries",
    "driver_code": "DEV",
    "driver_number": "21",
    "driver_name": "Nyck de Vries",
    "driver_nationality": "Dutch",
    "constructors": [
      "Williams"
    ],
    "constructor_ids": [
      "williams"
    ]
  },
  {
    "year": 2022,
    "position": 22,
    "position_text": "22",
    "points": 0.0,
    "wins": 0,
    "driver_id": "hulkenberg",
    "driver_code": "HUL",
    "driver_number": "27",
    "driver_name": "Nico H\u00fclkenberg",
    "driver_nationality": "German",
    "constructors": [
      "Aston Martin"
    ],
    "constructor_ids": [
      "aston_martin"
    ]
  }
]