[
  {
    "pace_rank": 1,
    "Driver": "VER",
    "Team": "Red Bull Racing",
    "DriverNumber": "1",
    "clean_laps": 45,
    "average_lap_seconds": 95.506,
    "median_lap_seconds": 95.127,
    "best_lap_seconds": 93.365,
    "lap_time_std_seconds": 1.714,
    "gap_to_best_avg_seconds": 0.0
  },
  {
    "pace_rank": 2,
    "Driver": "LEC",
    "Team": "Ferrari",
    "DriverNumber": "16",
    "clean_laps": 45,
    "average_lap_seconds": 96.029,
    "median_lap_seconds": 95.393,
    "best_lap_seconds": 94.304,
    "lap_time_std_seconds": 2.211,
    "gap_to_best_avg_seconds": 0.523
  },
  {
    "pace_rank": 3,
    "Driver": "PIA",
    "Team": "McLaren",
    "DriverNumber": "81",
    "clean_laps": 45,
    "average_lap_seconds": 96.011,
    "median_lap_seconds": 95.418,
    "best_lap_seconds": 94.086,
    "lap_time_std_seconds": 2.094,
    "gap_to_best_avg_seconds": 0.505
  },
  {
    "pace_rank": 4,
    "Driver": "RUS",
    "Team": "Mercedes",
    "DriverNumber": "63",
    "clean_laps": 45,
    "average_lap_seconds": 95.998,
    "median_lap_seconds": 95.482,
    "best_lap_seconds": 94.592,
    "lap_time_std_seconds": 1.465,
    "gap_to_best_avg_seconds": 0.492
  },
  {
    "pace_rank": 5,
    "Driver": "SAI",
    "Team": "Williams",
    "DriverNumber": "55",
    "clean_laps": 45,
    "average_lap_seconds": 96.132,
    "median_lap_seconds": 95.49,
    "best_lap_seconds": 94.496,
    "lap_time_std_seconds": 1.844,
    "gap_to_best_avg_seconds": 0.626
  },
  {
    "pace_rank": 6,
    "Driver": "ANT",
    "Team": "Mercedes",
    "DriverNumber": "12",
    "clean_laps": 45,
    "average_lap_seconds": 95.67,
    "median_lap_seconds": 95.615,
    "best_lap_seconds": 93.998,
    "lap_time_std_seconds": 1.03,
    "gap_to_best_avg_seconds": 0.164
  },
  {
    "pace_rank": 7,
    "Driver": "NOR",
    "Team": "McLaren",
    "DriverNumber": "4",
    "clean_laps": 45,
    "average_lap_seconds": 95.891,
    "median_lap_seconds": 95.68,
    "best_lap_seconds": 93.965,
    "lap_time_std_seconds": 1.799,
    "gap_to_best_avg_seconds": 0.385
  },
  {
    "pace_rank": 8,
    "Driver": "HAD",
    "Team": "Racing Bulls",
    "DriverNumber": "6",
    "clean_laps": 45,
    "average_lap_seconds": 96.345,
    "median_lap_seconds": 95.7,
    "best_lap_seconds": 94.62,
    "lap_time_std_seconds": 1.858,
    "gap_to_best_avg_seconds": 0.839
  },
  {
    "pace_rank": 9,
    "Driver": "HAM",
    "Team": "Ferrari",
    "DriverNumber": "44",
    "clean_laps": 45,
    "average_lap_seconds": 96.567,
    "median_lap_seconds": 95.994,
    "best_lap_seconds": 94.553,
    "lap_time_std_seconds": 2.412,
    "gap_to_best_avg_seconds": 1.061
  },
  {
    "pace_rank": 10,
    "Driver": "HUL",
    "Team": "Kick Sauber",
    "DriverNumber": "27",
    "clean_laps": 45,
    "average_lap_seconds": 96.449,
    "median_lap_seconds": 96.18,
    "best_lap_seconds": 94.592,
    "lap_time_std_seconds": 2.278,
    "gap_to_best_avg_seconds": 0.943
  },
  {
    "pace_rank": 11,
    "Driver": "OCO",
    "Team": "Haas F1 Team",
    "DriverNumber": "31",
    "clean_laps": 45,
    "average_lap_seconds": 96.639,
    "median_lap_seconds": 96.234,
    "best_lap_seconds": 94.557,
    "lap_time_std_seconds": 2.365,
    "gap_to_best_avg_seconds": 1.133
  },
  {
    "pace_rank": 12,
    "Driver": "TSU",
    "Team": "Red Bull Racing",
    "DriverNumber": "22",
    "clean_laps": 43,
    "average_lap_seconds": 96.402,
    "median_lap_seconds": 96.298,
    "best_lap_seconds": 94.967,
    "lap_time_std_seconds": 1.022,
    "gap_to_best_avg_seconds": 0.896
  },
  {
    "pace_rank": 13,
    "Driver": "ALB",
    "Team": "Williams",
    "DriverNumber": "23",
    "clean_laps": 28,
    "average_lap_seconds": 97.122,
    "median_lap_seconds": 96.401,
    "best_lap_seconds": 95.184,
    "lap_time_std_seconds": 3.129,
    "gap_to_best_avg_seconds": 1.616
  },
  {
    "pace_rank": 14,
    "Driver": "BEA",
    "Team": "Haas F1 Team",
    "DriverNumber": "87",
    "clean_laps": 45,
    "average_lap_seconds": 96.814,
    "median_lap_seconds": 96.53,
    "best_lap_seconds": 94.519,
    "lap_time_std_seconds": 1.918,
    "gap_to_best_avg_seconds": 1.308
  },
  {
    "pace_rank": 15,
    "Driver": "LAW",
    "Team": "Racing Bulls",
    "DriverNumber": "30",
    "clean_laps": 42,
    "average_lap_seconds": 96.553,
    "median_lap_seconds": 96.833,
    "best_lap_seconds": 94.837,
    "lap_time_std_seconds": 0.961,
    "gap_to_best_avg_seconds": 1.047
  },
  {
    "pace_rank": 16,
    "Driver": "ALO",
    "Team": "Aston Martin",
    "DriverNumber": "14",
    "clean_laps": 45,
    "average_lap_seconds": 96.959,
    "median_lap_seconds": 96.956,
    "best_lap_seconds": 95.629,
    "lap_time_std_seconds": 0.8,
    "gap_to_best_avg_seconds": 1.453
  },
  {
    "pace_rank": 17,
    "Driver": "GAS",
    "Team": "Alpine",
    "DriverNumber": "10",
    "clean_laps": 45,
    "average_lap_seconds": 96.946,
    "median_lap_seconds": 96.997,
    "best_lap_seconds": 95.674,
    "lap_time_std_seconds": 0.629,
    "gap_to_best_avg_seconds": 1.44
  },
  {
    "pace_rank": 18,
    "Driver": "COL",
    "Team": "Alpine",
    "DriverNumber": "43",
    "clean_laps": 44,
    "average_lap_seconds": 97.746,
    "median_lap_seconds": 97.244,
    "best_lap_seconds": 95.78,
    "lap_time_std_seconds": 2.749,
    "gap_to_best_avg_seconds": 2.24
  }
]