{
  "year": 2021,
  "round": 10,
  "event_input": "British Grand Prix",
  "event_name": "British Grand Prix",
  "official_event_name": "FORMULA 1 PIRELLI BRITISH GRAND PRIX 2021",
  "country": "Great Britain",
  "location": "Silverstone",
  "event_slug": "british-grand-prix",
  "session_input": "Race",
  "session_slug": "race",
  "generated_output_dir": "/Users/light/jarvis/00 Light/Projects/f1-stats-site/data-pipeline/output/events/2021/british-grand-prix/race",
  "source": "FastF1",
  "rows_laps": 925,
  "drivers": [
    "ALO",
    "BOT",
    "GAS",
    "GIO",
    "HAM",
    "LAT",
    "LEC",
    "MAZ",
    "MSC",
    "NOR",
    "OCO",
    "PER",
    "RAI",
    "RIC",
    "RUS",
    "SAI",
    "STR",
    "TSU",
    "VET"
  ],
  "rows_clean_laps": 823,
  "rows_pace": 19,
  "rows_stints": 41,
  "rows_pit_stops": 23,
  "rows_tyre_usage": 3
}